{"cameraMode":{"drawMode":0,"name":"Shaded","section":"Shading Mode"},"sceneLighting":true,"audioPlay":false,"sceneViewState":{"m_AlwaysRefresh":false,"showFog":false,"showSkybox":false,"showFlares":false,"showImageEffects":false,"showParticleSystems":false,"showVisualEffectGraphs":true,"m_FxEnabled":true},"in2DMode":false,"pivot":{"x":-149.80099487304688,"y":-43.8930549621582,"z":39.0380859375},"rotation":{"x":-0.13907469809055329,"y":0.5688949227333069,"z":-0.09852993488311768,"w":-0.8043157458305359},"size":66.66950988769531,"orthographic":false}