{"cameraMode":{"drawMode":0,"name":"Shaded","section":"Shading Mode"},"sceneLighting":true,"audioPlay":false,"sceneViewState":{"m_AlwaysRefresh":false,"showFog":false,"showSkybox":false,"showFlares":false,"showImageEffects":false,"showParticleSystems":false,"showVisualEffectGraphs":true,"m_FxEnabled":true},"in2DMode":false,"pivot":{"x":-96.32341003417969,"y":-41.866336822509769,"z":20.46982192993164},"rotation":{"x":-0.1589752584695816,"y":0.6219427585601807,"z":-0.13067178428173066,"w":-0.7552711963653565},"size":70.95230102539063,"orthographic":false}